README.rst
setup.py
cryptology/__init__.py
cryptology/client.py
cryptology/common.py
cryptology/exceptions.py
cryptology/market_data_client.py
cryptology/parallel.py
cryptology_ws_client.egg-info/PKG-INFO
cryptology_ws_client.egg-info/SOURCES.txt
cryptology_ws_client.egg-info/dependency_links.txt
cryptology_ws_client.egg-info/requires.txt
cryptology_ws_client.egg-info/top_level.txt