Metadata-Version: 2.1
Name: cryptology-ws-client
Version: 1.1.5
Summary: Cryptology webscoket client
Home-page: https://github.com/CryptologyExchange/cryptology-ws-client-python
Author: Cryptology
Author-email: s.prikazchikov@cryptology.com
License: UNKNOWN
Platform: UNKNOWN
Requires-Python: >= 3.6
Provides-Extra: devel
